LICENSE
README.md
pyproject.toml
armory/examples/__init__.py
armory/examples/version.py
armory/examples/image_classification/food101.py
armory/examples/object_detection/coco_fasterrcnn_resnet50.py
armory/examples/object_detection/license_plates_yolos.py
armory/examples/object_detection/license_plates_yolov5.py
armory/examples/object_detection/visdrone_yolov5.py
armory/examples/object_detection/visdrone_yolov5_robustdpatch.py
armory/examples/object_detection/datasets/visdrone.py
armory/examples/utils/__init__.py
armory/examples/utils/args.py
armory_examples-24.6.1.dist-info/METADATA
armory_examples-24.6.1.dist-info/WHEEL
armory_examples-24.6.1.dist-info/licenses/LICENSE
armory_examples-24.6.1.dist-info/RECORD
