Metadata-Version: 2.3
Name: armory-examples
Version: 24.6.1
Summary: TwoSix Armory Adversarial Robustness Library Examples
Author-email: Two Six Technologies <armory@twosixtech.com>
License-Expression: MIT
License-File: LICENSE
Classifier: Development Status :: 4 - Beta
Classifier: License :: OSI Approved :: MIT License
Classifier: Programming Language :: Python :: 3
Classifier: Topic :: Scientific/Engineering :: Artificial Intelligence
Requires-Python: >=3.8
Requires-Dist: adversarial-robustness-toolbox
Requires-Dist: armory-library
Requires-Dist: datasets
Requires-Dist: huggingface-hub
Requires-Dist: rich
Requires-Dist: transformers
Provides-Extra: all
Requires-Dist: albumentations<1.4.1; extra == 'all'
Requires-Dist: captum; extra == 'all'
Requires-Dist: scikit-learn>=1.2; extra == 'all'
Requires-Dist: tidecv; extra == 'all'
Requires-Dist: xaitk-saliency; extra == 'all'
Requires-Dist: yolov5; extra == 'all'
Provides-Extra: cv
Requires-Dist: albumentations<1.4.1; extra == 'cv'
Requires-Dist: captum; extra == 'cv'
Requires-Dist: scikit-learn>=1.2; extra == 'cv'
Requires-Dist: tidecv; extra == 'cv'
Requires-Dist: xaitk-saliency; extra == 'cv'
Requires-Dist: yolov5; extra == 'cv'
